[
  {
    "id": 1,
    "words": "你值得这世间，所有的<link={1}>_____</link>",
    "title": "",
    "": ""
  },
  {
    "id": 2,
    "words": "没有永恒的黑夜，只有<link={1}>_____</link>",
    "title": "",
    "": ""
  },
  {
    "id": 3,
    "words": "皎皎清月下，<link={1}>_____</link>",
    "title": "",
    "": ""
  },
  {
    "id": 4,
    "words": "我们征服的不是山，而是<link={1}>_____</link>",
    "title": "",
    "": ""
  },
  {
    "id": 5,
    "words": "眼里有<link={1}>_____</link>",
    "title": "",
    "": ""
  },
  {
    "id": 6,
    "words": "心中有<link={1}>_____",
    "title": "",
    "": ""
  },
  {
    "id": 7,
    "words": "希望你也真心喜欢自己，这并不容易，但从爱上自己的那一天起，人生才真正开始，<link={1}>_____</link>",
    "title": "",
    "": ""
  },
  {
    "id": 8,
    "words": "也许，我们永远长不大，那么，就在这继续长大的日子里：多一点尊重自己的感觉，多一点理解自己的脆弱，多一点信任自己的潜能，多一点关心自己的起居饮食，<link={1}>_____</link>",
    "title": "",
    "": ""
  },
  {
    "id": 9,
    "words": "我们要学会接受，接受有些愿望注定无法实现，有些关系注定无法继续，<link={1}>_____</link>",
    "title": "",
    "": ""
  },
  {
    "id": 10,
    "words": "在所有别人能给你造成的伤害中,破坏性最强、后果持续最久的一种,是让你怀疑自己配不上拥有任何好的事物，<link={1}>_____</link>",
    "title": "",
    "": ""
  },
  {
    "id": 11,
    "words": "总想着别人的感受，灵魂就回不到自己的身体里，<link={1}>_____</link>",
    "title": "",
    "": ""
  },
  {
    "id": 12,
    "words": "总有一天你会明白，真正能治愈你的，从来不是时间，而是你心里的那段释怀和格局，<link={1}>_____</link>",
    "title": "",
    "": ""
  },
  {
    "id": 13,
    "words": "我将玫瑰藏于身后，风起花落，从此鲜花赠自己，纵马踏花向自由，<link={1}>_____</link>",
    "title": "",
    "": ""
  },
  {
    "id": 14,
    "words": "心平能愈三千疾，凡事拈花自在笑，<link={1}>_____</link>",
    "title": "",
    "": ""
  },
  {
    "id": 15,
    "words": "生活能渡的，是愿意自渡的人，<link={1}>_____</link>",
    "title": "",
    "": ""
  },
  {
    "id": 16,
    "words": "遇见，获得，失去，成长，释怀，完结。我与旧事归于尽，来年依旧迎花开，<link={1}>_____</link>",
    "title": "",
    "": ""
  },
  {
    "id": 17,
    "words": "你的旅程是独特的，不要和别人比较，<link={1}>_____</link>",
    "title": "",
    "": ""
  },
  {
    "id": 18,
    "words": "有时候，最困难的事情，也是最值得的事情，<link={1}>_____</link>",
    "title": "",
    "": ""
  },
  {
    "id": 19,
    "words": "你的心灵需要阳光，就像植物需要阳光一样，<link={1}>_____</link>",
    "title": "",
    "": ""
  },
  {
    "id": 20,
    "words": "你的心灵健康是一切成功的基石，照顾好它，就是照顾好你的未来，<link={1}>_____</link>",
    "title": "",
    "": ""
  },
  {
    "id": 21,
    "words": "你的旅程是独一无二的，不要害怕走自己的路，<link={1}>_____</link>",
    "title": "",
    "": ""
  },
  {
    "id": 22,
    "words": "你的价值不在于你拥有什么，而在于你是谁，<link={1}>_____</link>",
    "title": "",
    "": ""
  },
  {
    "id": 23,
    "words": "你的心灵需要你的关怀和呵护，就像一棵树需要水和阳光，<link={1}>_____</link>",
    "title": "",
    "": ""
  },
  {
    "id": 24,
    "words": "你的内心世界是一片神奇的土地，需要你细心耕耘，<link={1}>_____</link>",
    "title": "",
    "": ""
  },
  {
    "id": 25,
    "words": "请记住，你不是一个人在战斗，总有人愿意倾听你的故事，<link={1}>_____</link>",
    "title": "",
    "": ""
  },
  {
    "id": 26,
    "words": "有时候，深呼吸，放慢脚步，就是最好的疗愈，<link={1}>_____</link>",
    "title": "",
    "": ""
  },
  {
    "id": 27,
    "words": "你的价值不是由别人的看法决定的，而是由你如何看待自己，<link={1}>_____</link>",
    "title": "",
    "": ""
  },
  {
    "id": 28,
    "words": "每个人都有自己的节奏，不要因为别人的快慢而失去自己的步伐，<link={1}>_____</link>",
    "title": "",
    "": ""
  },
  {
    "id": 29,
    "words": "每一天都是一个新的开始，不要害怕重新开始，<link={1}>_____</link>",
    "title": "",
    "": ""
  },
  {
    "id": 30,
    "words": "你的心灵健康是一切成功的基石，照顾好它，就是照顾好你的未来，<link={1}>_____</link>",
    "title": "",
    "": ""
  },
  {
    "id": 100,
    "words": "每个夜晚的星空都独一无二，就像人生旅程，每一步都充满了未知与奇迹。",
    "title": "简一",
    "": ""
  },
  {
    "id": 101,
    "words": "即使在最艰难的时刻，也请记得，希望从未离开。",
    "title": "莫夕颜",
    "": ""
  },
  {
    "id": 102,
    "words": "星星之所以美丽，是因为它在黑暗中闪烁；你之所以独特，是因为你在人群中坚持自我。",
    "title": "少泽",
    "": ""
  },
  {
    "id": 103,
    "words": "每个人的生命中都有一颗属于自己的星星，无论多么黑暗，它都会为你闪烁。",
    "title": "幻念",
    "": ""
  },
  {
    "id": 104,
    "words": "就算失败，我也想知道，自己倒在距离终点多远的地方。",
    "title": "安夏",
    "": ""
  },
  {
    "id": 105,
    "words": "总有一天你会明白，真正能治愈你的，从来不是时间，而是你心里的那段释怀和格局。",
    "title": "彩虹症",
    "": ""
  },
  {
    "id": 106,
    "words": "在你坚持不住的时候，记得告诉自己：想一千次，不如去做一次。",
    "title": "自我",
    "": ""
  },
  {
    "id": 107,
    "words": "我将玫瑰藏于身后，风起花落，从此鲜花赠自己，纵马踏花向自由。",
    "title": "龙人",
    "": ""
  },
  {
    "id": 108,
    "words": "生活能渡的，是愿意自渡的人。",
    "title": "云凤",
    "": ""
  },
  {
    "id": 109,
    "words": "心平能愈三千疾，凡事拈花自在笑。",
    "title": "风雅颂",
    "": ""
  },
  {
    "id": 110,
    "words": "当你能量越来越高的时候，你开始真正理解每一个人，没有好坏，没有对错，只是他处在不同的能量频率，呈现出了不同的状态，做了不同的选择。言慢者贵，性柔者富，德厚者旺。请允许自己做自己，也允许别人做别人，你会活得更洒脱。",
    "title": "尘缘旧",
    "": ""
  },
  {
    "id": 111,
    "words": "每错的一道题，每丢的一分，都是为了遇见对的人；而你们每对的一道题，每得的一分，都是为了遇见更好的自己。",
    "title": "泪妆",
    "": ""
  },
  {
    "id": 112,
    "words": "遇见，获得，失去，成长，释怀，完结。我与旧事归于尽，来年依旧迎花开。",
    "title": "露华浓",
    "": ""
  },
  {
    "id": 113,
    "words": "不要指责当时的自己，她当时一个人站在大雾里也很迷茫。",
    "title": "忆白",
    "": ""
  },
  {
    "id": 114,
    "words": "治愈人心的从来都不是句子，而是我们内心的深情流露。",
    "title": "青山隐",
    "": ""
  },
  {
    "id": 115,
    "words": "自由不是得到你爱的东西，而是爱你得到的东西。",
    "title": "晚风",
    "": ""
  },
  {
    "id": 116,
    "words": "当你穿过了暴风雨，你就不再是原来的那个人。",
    "title": "浅时光",
    "": ""
  },
  {
    "id": 117,
    "words": "人生最精彩的不是成功的那一瞬间，而是回头看，那段漆黑看似没有尽头、苦苦摸索的过程。",
    "title": "叮咚",
    "": ""
  },
  {
    "id": 118,
    "words": "你不必对自己说“努力面对”，尽力做好就可以了。",
    "title": "肆意",
    "": ""
  },
  {
    "id": 119,
    "words": "不要太乖，不想做的事可以拒绝，做不到的事不用勉强，不喜欢的话假装没听见。",
    "title": "樱花殇",
    "": ""
  },
  {
    "id": 120,
    "words": "体验生命，而非演绎完美。看花开，看水流，看日落。心怀热爱，尽兴生活，很多事情不需要意义。",
    "title": "凡尘客",
    "": ""
  }
]